LICENSE
README.md
pyproject.toml
setup.py
survival_distributions/__init__.py
survival_distributions/exponential.py
survival_distributions/log_logistic.py
survival_distributions/log_normal.py
survival_distributions/logistic.py
survival_distributions/mixture_same_family.py
survival_distributions/normal.py
survival_distributions/pareto.py
survival_distributions/survival_distribution.py
survival_distributions/transformed_distribution.py
survival_distributions/uniform.py
survival_distributions/weibull.py
survival_distributions.egg-info/PKG-INFO
survival_distributions.egg-info/SOURCES.txt
survival_distributions.egg-info/dependency_links.txt
survival_distributions.egg-info/requires.txt
survival_distributions.egg-info/top_level.txt