Metadata-Version: 2.1
Name: survival-distributions
Version: 0.0.3
Summary: Extended functionality for univariate probability distributions in PyTorch
Home-page: https://github.com/shchur/survival_distributions
Author: Oleksandr Shchur
Author-email: Oleksandr Shchur <oleks.shchur@gmail.com>
License: MIT
Project-URL: Homepage, https://github.com/shchur/survival_distributions
Platform: UNKNOWN
Classifier: Programming Language :: Python :: 3
Classifier: License :: OSI Approved :: MIT License
Classifier: Operating System :: OS Independent
Requires-Python: >=3.7
License-File: LICENSE
